LEVEL_6-Module-Hierarchy-and-Testbenches/Q49_COUNTER.v
module Q49 (
    input wire Clock,Reset,UpDown, output reg [3:0] Counter 
);
    always @(posedge Clock) begin
        if (Reset) begin
            Counter<= 4'b0000;
        end
        else if (UpDown) begin
            Counter<= Counter+4'b0001;
        end 
        else begin
            Counter<= Counter-4'b0001;
        end
    end
endmodule

LEVEL_6-Module-Hierarchy-and-Testbenches/tb_q49.v
module tb_q49;
reg Clock;
reg Reset;
reg UpDown;

wire [3:0] Counter;

Q49 dut(
    .Reset(Reset),.Clock(Clock),.UpDown(UpDown),.Counter(Counter)
);

always #5 Clock=~Clock;

initial begin
    $dumpfile("q49.vcd");
    $dumpvars(0,tb_q49);

    $monitor("Clock=%b,Reset=%b,Updown=%b,Counter=%b",Clock,Reset,UpDown,Counter);

    Clock=0;Reset=1;UpDown=1;#10;
    Reset=0;UpDown=1;#70;
    UpDown=0;#30;
    Reset=1;#10;
    Reset=0;UpDown=1;#30;
    UpDown=0;#50;
    Reset=1;#10;
    UpDown=1;#170;
    $finish;
end
endmodule

LEVEL_6-Module-Hierarchy-and-Testbenches/q49.vcd
$date
	Wed Sep 02 18:15:33 2026
$end
$version
	Icarus Verilog
$end
$timescale
	1s
$end
$scope module tb_q49 $end
$var wire 4 ! Counter [3:0] $end
$var reg 1 " Clock $end
$var reg 1 # Reset $end
$var reg 1 $ UpDown $end
$scope module dut $end
$var wire 1 " Clock $end
$var wire 1 # Reset $end
$var wire 1 $ UpDown $end
$var reg 4 % Counter [3:0] $end
$upscope $end
$upscope $end
$enddefinitions $end
$comment Show the parameter values. $end
$dumpall
$end
#0
$dumpvars
bx %
1$
1#
0"
bx !
$end
#5
b0 !
b0 %
1"
#10
0"
0#
#15
b1 !
b1 %
1"
#20
0"
#25
b10 !
b10 %
1"
#30
0"
#35
b11 !
b11 %
1"
#40
0"
#45
b100 !
b100 %
1"
#50
0"
#55
b101 !
b101 %
1"
#60
0"
#65
b110 !
b110 %
1"
#70
0"
#75
b111 !
b111 %
1"
#80
0"
0$
#85
b110 !
b110 %
1"
#90
0"
#95
b101 !
b101 %
1"
#100
0"
#105
b100 !
b100 %
1"
#110
0"
1#
#115
b0 !
b0 %
1"
#120
0"
1$
0#
#125
b1 !
b1 %
1"
#130
0"
#135
b10 !
b10 %
1"
#140
0"
#145
b11 !
b11 %
1"
#150
0"
0$
#155
b10 !
b10 %
1"
#160
0"
#165
b1 !
b1 %
1"
#170
0"
#175
b0 !
b0 %
1"
#180
0"
#185
b1111 !
b1111 %
1"
#190
0"
#195
b1110 !
b1110 %
1"
#200
0"
1#
#205
b0 !
b0 %
1"
#210
0"
1$
