Level_4-Sequential_Circuits/q27_dffsync.v
module q27 (
    input wire clk,d,reset,output reg q
);
    always @(posedge clk) begin
        if(reset==1)
          q<=0;
        else
         q<=d;
    end
endmodule

Level_4-Sequential_Circuits/tb_q27dffsync.v
module tb_q27;
reg clk;
reg d;
reg reset;
wire q;

q27 uut(.clk(clk),.d(d),.reset(reset),.q(q));

initial begin
    $dumpfile("q27.vcd");
    $dumpvars(0,tb_q27);
    $monitor("D=%b,Clk=%b,Reset=%b,Q=%b",d,clk,reset,q);

    clk=0;
    d=0;reset=1;#10;
    d=1;reset=0;#12;
    d=1;reset=1;#15;
    d=0;reset=1;#17;
    d=0;reset=0;#14;
    $finish;
end

always #5 clk= ~clk;

endmodule

Level_4-Sequential_Circuits/q27.vcd
$date
	Sun Jul 12 21:52:11 2026
$end
$version
	Icarus Verilog
$end
$timescale
	1s
$end
$scope module tb_q27 $end
$var wire 1 ! q $end
$var reg 1 " clk $end
$var reg 1 # d $end
$var reg 1 $ reset $end
$scope module uut $end
$var wire 1 " clk $end
$var wire 1 # d $end
$var wire 1 $ reset $end
$var reg 1 ! q $end
$upscope $end
$upscope $end
$enddefinitions $end
$comment Show the parameter values. $end
$dumpall
$end
#0
$dumpvars
1$
0#
0"
x!
$end
#5
0!
1"
#10
0"
0$
1#
#15
1!
1"
#20
0"
#22
1$
#25
0!
1"
#30
0"
#35
1"
#37
0#
#40
0"
#45
1"
#50
0"
#54
0$
