Level_4-Sequential_Circuits/q31_4butupcount.v
module q31 (
    input wire Clock,output reg [3:0] Counter
);
initial begin
    Counter=0;
end
    always @(posedge Clock) begin
        Counter<= Counter+4'b0001;
    end
endmodule

Level_4-Sequential_Circuits/tb_q31upcounter.v
module tb_31;
reg Clock;
wire [3:0] Counter;

q31 uut(.Clock(Clock),.Counter(Counter));

initial begin
    $dumpfile("q31.vcd");
    $dumpvars(0,tb_31);
    $monitor("Clock=%b,Count=%b",Clock,Counter);
    Clock=0;
    #100;
    $finish;
end

always #5 Clock=~Clock;
endmodule

Level_4-Sequential_Circuits/q31.vcd
$date
	Fri Jul 17 23:31:41 2026
$end
$version
	Icarus Verilog
$end
$timescale
	1s
$end
$scope module tb_31 $end
$var wire 4 ! Counter [3:0] $end
$var reg 1 " Clock $end
$scope module uut $end
$var wire 1 " Clock $end
$var reg 4 # Counter [3:0] $end
$upscope $end
$upscope $end
$enddefinitions $end
$comment Show the parameter values. $end
$dumpall
$end
#0
$dumpvars
b0 #
0"
b0 !
$end
#5
b1 !
b1 #
1"
#10
0"
#15
b10 !
b10 #
1"
#20
0"
#25
b11 !
b11 #
1"
#30
0"
#35
b100 !
b100 #
1"
#40
0"
#45
b101 !
b101 #
1"
#50
0"
#55
b110 !
b110 #
1"
#60
0"
#65
b111 !
b111 #
1"
#70
0"
#75
b1000 !
b1000 #
1"
#80
0"
#85
b1001 !
b1001 #
1"
#90
0"
#95
b1010 !
b1010 #
1"
