Level_4-Sequential_Circuits/q32_updowncounter.v
module q32 (
    input wire Clock,Reset,UpDown, output reg [3:0] Counter
);
    always @(posedge Clock) begin
        if (Reset) begin
            Counter<= 4'b0000;
        end
        else if (UpDown) begin
            Counter<= Counter+4'b0001;
        end 
        else begin
            Counter<= Counter-4'b0001;
        end
    end
endmodule

Level_4-Sequential_Circuits/tb_q32updowncounter.v
module tb_q32;
reg Clock;
reg Reset;
reg UpDown;
wire [3:0] Counter;

q32 uut(.Clock(Clock),.Reset(Reset),.UpDown(UpDown),.Counter(Counter));

initial begin
    $dumpfile("q32.vcd");
    $dumpvars(0,tb_q32);
    $monitor("Clock=%b,reset=%b,Up/Down=%b,Counter=%b",Clock,Reset,UpDown,Counter);
    Clock=0;
    Reset=0;UpDown=1;#10;
    Reset=0;UpDown=1;#10;
    Reset=1;UpDown=0;#10;
    Reset=0;UpDown=1;#10;
    Reset=0;UpDown=1;#10;
    Reset=0;UpDown=1;#10;
    Reset=1;UpDown=1;#10;
    $finish;
end

always #5 Clock=~Clock;
endmodule

Level_4-Sequential_Circuits/q32.vcd
$date
	Sat Jul 18 23:24:46 2026
$end
$version
	Icarus Verilog
$end
$timescale
	1s
$end
$scope module tb_q32 $end
$var wire 4 ! Counter [3:0] $end
$var reg 1 " Clock $end
$var reg 1 # Reset $end
$var reg 1 $ UpDown $end
$scope module uut $end
$var wire 1 " Clock $end
$var wire 1 # Reset $end
$var wire 1 $ UpDown $end
$var reg 4 % Counter [3:0] $end
$upscope $end
$upscope $end
$enddefinitions $end
$comment Show the parameter values. $end
$dumpall
$end
#0
$dumpvars
bx %
1$
0#
0"
bx !
$end
#5
1"
#10
0"
#15
1"
#20
0"
0$
1#
#25
b0 !
b0 %
1"
#30
0"
1$
0#
#35
b1 !
b1 %
1"
#40
0"
#45
b10 !
b10 %
1"
#50
0"
#55
b11 !
b11 %
1"
#60
0"
1#
#65
b0 !
b0 %
1"
