Level_4-Sequential_Circuits/q34_clkdivider.v
module q34 (
    input wire Clock,Reset,output reg Slowclk
);
reg [1:0] Counter;
    always @(posedge Clock) begin
        if (Reset) begin
            Counter<=0;
            Slowclk<=0;
        end
        else if(Counter==3) begin
            Slowclk<=~Slowclk;
            Counter<=0;
        end
        else begin
            Counter<=Counter+1;
        end
    end
endmodule

Level_4-Sequential_Circuits/tb_q34clkdivider.v
module tb_q34;
reg Reset;
reg Clock;
wire Slowclk;
wire [1:0] Counter;

q34 uut(.Clock(Clock),.Reset(Reset),.Slowclk(Slowclk));

initial begin
    $dumpfile("q34.vcd");
    $dumpvars(0,tb_q34);
    $monitor("Clock=%b,Reset=%b,Slow_clock=%b",Clock,Reset,Slowclk);

    Clock=0;
    Reset=1;#10;
    Reset=0;#10;
    #100;
    $finish;
end
always #5 Clock=~Clock;
endmodule

Level_4-Sequential_Circuits/q34.vcd
$date
	Mon Jul 20 22:55:29 2026
$end
$version
	Icarus Verilog
$end
$timescale
	1s
$end
$scope module tb_q34 $end
$var wire 1 ! Slowclk $end
$var reg 1 " Clock $end
$var reg 1 # Reset $end
$scope module uut $end
$var wire 1 " Clock $end
$var wire 1 # Reset $end
$var reg 2 $ Counter [1:0] $end
$var reg 1 ! Slowclk $end
$upscope $end
$upscope $end
$enddefinitions $end
$comment Show the parameter values. $end
$dumpall
$end
#0
$dumpvars
bx $
1#
0"
x!
$end
#5
0!
b0 $
1"
#10
0"
0#
#15
b1 $
1"
#20
0"
#25
b10 $
1"
#30
0"
#35
b11 $
1"
#40
0"
#45
b0 $
1!
1"
#50
0"
#55
b1 $
1"
#60
0"
#65
b10 $
1"
#70
0"
#75
b11 $
1"
#80
0"
#85
b0 $
0!
1"
#90
0"
#95
b1 $
1"
#100
0"
#105
b10 $
1"
#110
0"
#115
b11 $
1"
