Level_4-Sequential_Circuits/q35_piso.v
module q35 (
    input wire Clock,Load,input wire [3:0] D, output wire Serialout
);
    reg [3:0] Register;
    always @(posedge Clock) begin
        if (Load) begin
            Register<=D;
        end 
        else begin
            Register<= {1'b0, Register [3:1]};    
        end
    end
    assign Serialout= Register [0];
endmodule

Level_4-Sequential_Circuits/tb_q35piso.v
module tb_q35;

reg Clock;
reg Load;
reg [3:0] D;
wire Serialout;
wire [3:0] Register;

q35 uut(.Clock(Clock),.Load(Load),.D(D),.Serialout(Serialout));

initial begin
    $dumpfile("q35.vcd");
    $dumpvars(0,tb_q35);
    $monitor("Clock=%b,Load=%b,SerialOut=%b",Clock,Load,Serialout);

    Clock=0;
    Load=1;D=4'b1011;#10;
    Load=0;#10;
    Load=0;#10
    Load=1;#5;
    Load=0;#10;
    #100;
    $finish;
end
always #5 Clock=~Clock;
endmodule

Level_4-Sequential_Circuits/q35.vcd
$date
	Tue Jul 21 22:29:16 2026
$end
$version
	Icarus Verilog
$end
$timescale
	1s
$end
$scope module tb_q35 $end
$var wire 1 ! Serialout $end
$var reg 1 " Clock $end
$var reg 4 # D [3:0] $end
$var reg 1 $ Load $end
$scope module uut $end
$var wire 1 " Clock $end
$var wire 4 % D [3:0] $end
$var wire 1 $ Load $end
$var wire 1 ! Serialout $end
$var reg 4 & Register [3:0] $end
$upscope $end
$upscope $end
$enddefinitions $end
$comment Show the parameter values. $end
$dumpall
$end
#0
$dumpvars
bx &
b1011 %
1$
b1011 #
0"
x!
$end
#5
1!
b1011 &
1"
#10
0"
0$
#15
b101 &
1"
#20
0"
#25
0!
b10 &
1"
#30
0"
1$
#35
1!
b1 &
1"
0$
#40
0"
#45
0!
b0 &
1"
