Level-5-Finite-State-Machines/q38_FSM_Controller.v
module q38 (
    input wire Reset,Clock,X, output wire Detector
);
    reg [1:0] Current_State,Next_State;
    parameter S0=2'b00;
    parameter S1=2'b01;
    parameter S2=2'b10;
    parameter S3=2'b11;
    always @(posedge Clock) begin
        if (Reset) begin
            Current_State<=S0;
        end 
        else begin
            Current_State<=Next_State;
        end
    end

    always @(*) begin
        case (Current_State)
            S0:begin
                if (X) begin
                    Next_State=S1;
                end 
                else begin
                    Next_State=S0;
                end
            end
            S1:begin
                if (X) begin
                    Next_State=S1;
                end 
                else begin
                    Next_State=S2;
                end
            end
            S2:begin
                if (X) begin
                    Next_State=S3;
                end else begin
                    Next_State=S0;
                end
            end
            S3:begin
                if (X) begin
                    Next_State=S1;
                end 
                else begin
                    Next_State=S2;
                end
            end
            default:Next_State=S0;
        endcase
    end

    assign Detector= (Current_State== S3);    
endmodule

Level-5-Finite-State-Machines/tb_q38.v
    module tb_q38;
    reg Reset;
    reg Clock;
    reg X;
    wire Detector;

    q38 uut(.Reset(Reset),.Clock(Clock),.X(X),.Detector(Detector));

    always #5 Clock=~Clock;

    initial begin
        $dumpfile("q38.vcd");
        $dumpvars(0,tb_q38);
        $monitor("Clock=%b,Reset=%b,X=%b,State=%b,Detector=%b", Clock,Reset,X,uut.Current_State,Detector);
    Clock = 0;
    Reset = 1;
    X = 0;#10;
    Reset = 0;X = 0;#10;
    X = 1;#10;
    X = 0;#10;
    X = 1;#10;
    X = 0;#10;
    X = 1;#10;
    X = 1;#10;
    X = 0;#10;
    X = 1;#10;
    $finish;
    end
    endmodule

Level-5-Finite-State-Machines/q38.vcd
$date
	Sat Jul 25 22:58:33 2026
$end
$version
	Icarus Verilog
$end
$timescale
	1s
$end
$scope module tb_q38 $end
$var wire 1 ! Detector $end
$var reg 1 " Clock $end
$var reg 1 # Reset $end
$var reg 1 $ X $end
$scope module uut $end
$var wire 1 " Clock $end
$var wire 1 # Reset $end
$var wire 1 $ X $end
$var wire 1 ! Detector $end
$var parameter 2 % S0 $end
$var parameter 2 & S1 $end
$var parameter 2 ' S2 $end
$var parameter 2 ( S3 $end
$var reg 2 ) Current_State [1:0] $end
$var reg 2 * Next_State [1:0] $end
$upscope $end
$upscope $end
$enddefinitions $end
$comment Show the parameter values. $end
$dumpall
b11 (
b10 '
b1 &
b0 %
$end
#0
$dumpvars
b0 *
bx )
0$
1#
0"
x!
$end
#5
0!
b0 )
1"
#10
0"
0#
#15
1"
#20
b1 *
0"
1$
#25
b1 )
1"
#30
b10 *
0"
0$
#35
b0 *
b10 )
1"
#40
b11 *
0"
1$
#45
b1 *
1!
b11 )
1"
#50
b10 *
0"
0$
#55
b0 *
0!
b10 )
1"
#60
b11 *
0"
1$
#65
b1 *
1!
b11 )
1"
#70
0"
#75
0!
b1 )
1"
#80
b10 *
0"
0$
#85
b0 *
b10 )
1"
#90
b11 *
0"
1$
#95
b1 *
1!
b11 )
1"
