Level-5-Finite-State-Machines/Q39-Vending_machine.v
module q39 (
    input wire Clock, Reset, Coin, output wire Dispense
);
reg [1:0] Current_State,Next_State;
parameter S0=2'b00;
parameter S1=2'b01;
parameter S2=2'b10;
always @(posedge Clock or posedge Reset) begin
    if (Reset) begin
        Current_State<=S0;
    end 
    else begin
        Current_State<=Next_State;
    end
end

always @(*) begin
    Next_State=Current_State;
    case (Current_State)
        S0:begin
            if (Coin) begin
                Next_State=S1;
            end 
            else begin
                Next_State=S0;
            end
        end
        S1:begin
            if (Coin) begin
                Next_State=S2;
            end 
            else begin
                Next_State=S1;
            end
        end
        S2:begin
            if (Coin) begin
                Next_State=S1;
            end 
            else begin
                Next_State=S0;
            end
        end
        default:Next_State=S0;
    endcase
end

assign Dispense=(Current_State==S2);

endmodule

Level-5-Finite-State-Machines/tb_q39.v
module tb_q39;
    reg Reset;
    reg Clock;
    reg Coin;
    wire Dispense;

    q39 uut(.Reset(Reset),.Clock(Clock),.Coin(Coin),.Dispense(Dispense));

    always #5 Clock=~Clock;

    initial begin
        $dumpfile("q39.vcd");
        $dumpvars(0,tb_q39);
        $monitor("Clock=%b,Reset=%b,COIN=%b,State=%b,Dispense=%b", Clock,Reset,Coin,uut.Current_State,Dispense);
    Clock = 0;
    Reset = 1;
Coin = 1;
#10;

Reset = 1;
#10;

Reset = 0;
Coin = 0;
#10;
Coin = 1;
#10;
Coin = 1;
#10;
Reset = 1;
#10;
Reset = 0;
#10;
$finish;
end
endmodule

Level-5-Finite-State-Machines/q39.vcd
$date
	Mon Jul 27 22:01:22 2026
$end
$version
	Icarus Verilog
$end
$timescale
	1s
$end
$scope module tb_q39 $end
$var wire 1 ! Dispense $end
$var reg 1 " Clock $end
$var reg 1 # Coin $end
$var reg 1 $ Reset $end
$scope module uut $end
$var wire 1 " Clock $end
$var wire 1 # Coin $end
$var wire 1 $ Reset $end
$var wire 1 ! Dispense $end
$var parameter 2 % S0 $end
$var parameter 2 & S1 $end
$var parameter 2 ' S2 $end
$var reg 2 ( Current_State [1:0] $end
$var reg 2 ) Next_State [1:0] $end
$upscope $end
$upscope $end
$enddefinitions $end
$comment Show the parameter values. $end
$dumpall
b10 '
b1 &
b0 %
$end
#0
$dumpvars
b1 )
b0 (
1$
1#
0"
0!
$end
#5
1"
#10
0"
#15
1"
#20
b0 )
0"
0#
0$
#25
1"
#30
b1 )
0"
1#
#35
b10 )
b1 (
1"
#40
0"
#45
b1 )
1!
b10 (
1"
#50
b1 )
0!
b0 (
0"
1$
#55
1"
#60
0"
0$
#65
b10 )
b1 (
1"
