Level-5-Finite-State-Machines/Q40_edge_detector.v
module q40 (
    input wire Reset,Clock, In, output wire Detector
);
    reg Current_State,Next_State;
    parameter S0=0;
    parameter S1=1;
    always @(posedge Clock or posedge Reset) begin
        if (Reset) begin
            Current_State<=S0;
        end else begin
            Current_State<=Next_State;
        end
    end

    always @(*) begin
        case (Current_State)
            S0:if (In) begin
                Next_State=S1;
            end else begin
                Next_State=S0;
            end 
            S1:if (In) begin
                Next_State=S1;
            end else begin
                Next_State=S0;
            end
            default:Next_State=S0;
        endcase
    end

    assign Detector= (Current_State==S0) && (In==1);
endmodule

Level-5-Finite-State-Machines/tb_q40.v
module tb_q40;
reg Reset;
    reg Clock;
    reg In;
    wire Detector;

    q40 uut(.Reset(Reset),.Clock(Clock),.In(In),.Detector(Detector));

    always #5 Clock=~Clock;

    initial begin
        $dumpfile("q40.vcd");
        $dumpvars(0,tb_q40);
        $monitor("Clock=%b,Reset=%b,IN=%b,State=%b,Detector=%b", Clock,Reset,In,uut.Current_State,Detector);
    Clock = 0;
Reset = 1;
In = 0;
#10;

Reset = 0;
In = 0;
#10;

In = 1;
#10;

In = 1;
#10;

In = 0;
#10;
In = 1;
#10;

Reset = 1;
#10;

Reset = 0;
#10;

$finish;
end
endmodule

Level-5-Finite-State-Machines/q40.vcd
$date
	Wed Jul 29 00:04:03 2026
$end
$version
	Icarus Verilog
$end
$timescale
	1s
$end
$scope module tb_q40 $end
$var wire 1 ! Detector $end
$var reg 1 " Clock $end
$var reg 1 # In $end
$var reg 1 $ Reset $end
$scope module uut $end
$var wire 1 " Clock $end
$var wire 1 ! Detector $end
$var wire 1 # In $end
$var wire 1 $ Reset $end
$var parameter 32 % S0 $end
$var parameter 32 & S1 $end
$var reg 1 ' Current_State $end
$var reg 1 ( Next_State $end
$upscope $end
$upscope $end
$enddefinitions $end
$comment Show the parameter values. $end
$dumpall
b1 &
b0 %
$end
#0
$dumpvars
0(
0'
1$
0#
0"
0!
$end
#5
1"
#10
0"
0$
#15
1"
#20
1(
1!
0"
1#
#25
0!
1'
1"
#30
0"
#35
1"
#40
0(
0"
0#
#45
0'
1"
#50
1(
1!
0"
1#
#55
0!
1'
1"
#60
1!
0'
0"
1$
#65
1"
#70
0"
0$
#75
0!
1'
1"
