Level-5-Finite-State-Machines/Q42-DATAPATH.v
module q42 (
    input wire Clock, Reset, enable, output reg [3:0] count
);
always @(posedge Clock or posedge Reset) begin
    if (Reset) begin
        count<=4'b0000;
    end 
    else begin
        if (enable) begin
            count<= count+1;
        end 
    end
end

endmodule

Level-5-Finite-State-Machines/Q42_FSM.v
module FSM (
    input wire Clock,Reset,Start, Stop, output reg enable
);
localparam IDLE = 1'b0;
localparam  RUNNING=1'b1;
reg Current_State;
reg Next_State;

always @(posedge Clock or posedge Reset)
begin
    if (Reset)
        Current_State <= IDLE;
    else
        Current_State <= Next_State;
end

always @(*) begin
    Next_State=Current_State;
    case (Current_State)
        IDLE:begin
            if (Start) begin
                Next_State=RUNNING;
            end 
            else begin
                Next_State=IDLE;
            end
        end
        RUNNING: begin
            if (Stop) begin
                Next_State=IDLE;
            end 
            else begin
                Next_State=RUNNING;    
            end
        end
        default:Next_State=IDLE;
    endcase
end

always @(*) begin
    case (Current_State)

        IDLE: begin
            enable = 1'b0;
        end

        RUNNING: begin
            enable = 1'b1;
        end

        default: begin
            enable = 1'b0;
        end

    endcase
end
endmodule

Level-5-Finite-State-Machines/Q42_top.v
module Top (
    input wire Clock,
    input wire Reset,
    input wire Start,
    input wire Stop,
    output wire [3:0] count
);

    wire enable;

    FSM fsm_instance (
        .Clock(Clock),
        .Reset(Reset),
        .Start(Start),
        .Stop(Stop),
        .enable(enable)
    );

    q42 datapath_instance (
        .Clock(Clock),
        .Reset(Reset),
        .enable(enable),
        .count(count)
    );

endmodule

Level-5-Finite-State-Machines/Q42_tb.v
module tb_q42;
reg Clock;
reg Reset;
reg Start;
reg Stop;
wire [3:0] count;

Top dut(.Clock(Clock),.Reset(Reset),.Start(Start),.Stop(Stop),.count(count));

initial begin
    Clock=0;
end

always #5 Clock=~Clock;

initial begin
    Reset=1;Start=0;Stop=0;#10;
    Reset=0;#10;
    Start=1;#10;
    Start=0;#30;
    Stop=1;#10;
    Stop=0;#20;
    $finish;
end
initial begin
    $dumpfile("q42.vcd");
    $dumpvars(0,tb_q42);
    $monitor("Time=%0t Reset=%b Start=%b Stop=%b Count=%d",$time, Reset, Start, Stop, count);
end
endmodule

Level-5-Finite-State-Machines/q42.vcd
$date
	Sun Aug 09 13:07:34 2026
$end
$version
	Icarus Verilog
$end
$timescale
	1s
$end
$scope module tb_q42 $end
$var wire 4 ! count [3:0] $end
$var reg 1 " Clock $end
$var reg 1 # Reset $end
$var reg 1 $ Start $end
$var reg 1 % Stop $end
$scope module dut $end
$var wire 1 " Clock $end
$var wire 1 # Reset $end
$var wire 1 $ Start $end
$var wire 1 % Stop $end
$var wire 1 & enable $end
$var wire 4 ' count [3:0] $end
$scope module datapath_instance $end
$var wire 1 " Clock $end
$var wire 1 # Reset $end
$var wire 1 & enable $end
$var reg 4 ( count [3:0] $end
$upscope $end
$scope module fsm_instance $end
$var wire 1 " Clock $end
$var wire 1 # Reset $end
$var wire 1 $ Start $end
$var wire 1 % Stop $end
$var parameter 1 ) IDLE $end
$var parameter 1 * RUNNING $end
$var reg 1 + Current_State $end
$var reg 1 , Next_State $end
$var reg 1 & enable $end
$upscope $end
$upscope $end
$upscope $end
$enddefinitions $end
$comment Show the parameter values. $end
$dumpall
1*
0)
$end
#0
$dumpvars
0,
0+
b0 (
b0 '
0&
0%
0$
1#
0"
b0 !
$end
#5
1"
#10
0"
0#
#15
1"
#20
1,
0"
1$
#25
1&
1+
1"
#30
0"
0$
#35
b1 !
b1 '
b1 (
1"
#40
0"
#45
b10 !
b10 '
b10 (
1"
#50
0"
#55
b11 !
b11 '
b11 (
1"
#60
0,
0"
1%
#65
0&
b100 !
b100 '
b100 (
0+
1"
#70
0"
0%
