Level-5-Finite-State-Machines/Q43_TC.v
module q43 (
    input wire Clock,Reset,Emergency, output reg Light0, Light1, Light2, Light3, Emergency_Out 
);
    reg [2:0] current_state;
    reg [2:0] next_state;
    reg [2:0] previous_state;
    parameter S0= 3'b000;
    parameter S1= 3'b001;
    parameter S2= 3'b010;
    parameter S3= 3'b011;
    parameter EMERGENCY= 3'b100;
    wire [3:0] Lights;
    assign Lights = {Light3, Light2, Light1, Light0};

    always @(posedge Clock or posedge Reset) begin
    if (Reset) begin
        current_state  <= S0;
        previous_state <= S0;
    end
    else begin
    if (Emergency && current_state != EMERGENCY)
        previous_state <= current_state;
        current_state <= next_state;
    end
end


always @(*) begin
    next_state=current_state;
    if (Emergency) begin
        next_state=EMERGENCY;
    end 
    else begin
        case(current_state)
        S0:next_state=S1;
        S1:next_state=S2;
        S2:next_state=S3;
        S3:next_state=S0;
        EMERGENCY:begin
            next_state=previous_state;
        end

        default:next_state=current_state;
        endcase

    end
end

always @(*) begin
    Light0=1'b0;
    Light1=1'b0;
    Light2=1'b0;
    Light3=1'b0;
    Emergency_Out=1'b0;
    case (current_state)
        S0:begin
            Light0=1'b1;
        end 
        S1:begin
            Light1=1'b1;
        end
        S2:begin
            Light2=1'b1;
        end
        S3:begin
            Light3=1'b1;
        end
            EMERGENCY:begin
            Emergency_Out=1'b1;
        end
        default:begin
            
        end
    endcase
end
endmodule

Level-5-Finite-State-Machines/tb_q43.v
module tb_q43;
reg Reset;
reg Clock;
reg Emergency;
wire Light0, Light1, Light2, Light3, Emergency_Out;
wire [3:0] Lights;
assign Lights = {Light3, Light2, Light1, Light0};

q43 dut(.Reset(Reset),.Clock(Clock),.Emergency(Emergency),.Light0(Light0),.Light1(Light1),.Light2(Light2),.Light3(Light3),.Emergency_Out(Emergency_Out));

always #5 Clock=~Clock;


initial begin
    $dumpfile("q43.vcd");
    $dumpvars(0,tb_q43);

    $monitor("Clock=%b Reset=%b Emergency=%b Lights=%b Emergency_Out=%b",Clock, Reset, Emergency,Lights,Emergency_Out);
    Clock=0;
    Reset=1;Emergency=0;#10;
    Reset=0;Emergency=0;#10;
    Reset=0;Emergency=1;#10;
    Reset=1;Emergency=1;#10;
    Reset=0;Emergency=0;#10;
    Reset=0;Emergency=0;#10;
    Reset=0;Emergency=0;#10;
    Reset=0;Emergency=1;#10;
    Reset=0;Emergency=0;#10;
    $finish;
end
endmodule

Level-5-Finite-State-Machines/q43.vcd
$date
	Wed Aug 12 11:44:22 2026
$end
$version
	Icarus Verilog
$end
$timescale
	1s
$end
$scope module tb_q43 $end
$var wire 4 ! Lights [3:0] $end
$var wire 1 " Light3 $end
$var wire 1 # Light2 $end
$var wire 1 $ Light1 $end
$var wire 1 % Light0 $end
$var wire 1 & Emergency_Out $end
$var reg 1 ' Clock $end
$var reg 1 ( Emergency $end
$var reg 1 ) Reset $end
$scope module dut $end
$var wire 1 ' Clock $end
$var wire 1 ( Emergency $end
$var wire 1 ) Reset $end
$var wire 4 * Lights [3:0] $end
$var parameter 3 + EMERGENCY $end
$var parameter 3 , S0 $end
$var parameter 3 - S1 $end
$var parameter 3 . S2 $end
$var parameter 3 / S3 $end
$var reg 1 & Emergency_Out $end
$var reg 1 % Light0 $end
$var reg 1 $ Light1 $end
$var reg 1 # Light2 $end
$var reg 1 " Light3 $end
$var reg 3 0 current_state [2:0] $end
$var reg 3 1 next_state [2:0] $end
$var reg 3 2 previous_state [2:0] $end
$upscope $end
$upscope $end
$enddefinitions $end
$comment Show the parameter values. $end
$dumpall
b11 /
b10 .
b1 -
b0 ,
b100 +
$end
#0
$dumpvars
b0 2
b1 1
b0 0
b1 *
1)
0(
0'
0&
1%
0$
0#
0"
b1 !
$end
#5
1'
#10
0'
0)
#15
1$
b10 *
b10 !
0%
b10 1
b1 0
1'
#20
b10 *
b10 !
1$
b100 1
0'
1(
#25
b0 *
b0 !
0$
b100 0
b1 2
1'
#30
b1 *
b1 !
1%
b100 1
b0 2
b0 0
0'
1)
#35
1'
#40
b1 *
b1 !
1%
b1 1
0'
0(
0)
#45
1$
b10 *
b10 !
0%
b10 1
b1 0
1'
#50
0'
#55
1#
b100 *
b100 !
0$
b11 1
b10 0
1'
#60
0'
#65
1"
b1000 *
b1000 !
0#
b0 1
b11 0
1'
#70
b1000 *
b1000 !
1"
b100 1
0'
1(
#75
b0 *
b0 !
0"
b100 0
b11 2
1'
#80
b11 1
0'
0(
#85
b1000 *
b1000 !
1"
b0 1
b11 0
1'
