Level-5-Finite-State-Machines/Q44_PL.v
module Q44 (
    input wire Clock,Reset, Entry,Exit,Emergency,output reg Empty_Out,Occupied_Out,Full_Out,Emergency_Out
);
    reg [1:0] current_state;
    reg [1:0] next_state;
    parameter Empty = 2'b00;
    parameter Occupied = 2'b01;
    parameter Full = 2'b10;
    parameter EMERGENCY = 2'b11;
    wire [2:0] Status;
    assign Status = {Full_Out, Occupied_Out, Empty_Out};

always @(posedge Clock or posedge Reset) begin
    if (Reset) begin
        current_state<=Empty;
    end 
    else begin
        current_state<=next_state;
    end
end

always @(*) begin
    next_state=current_state;
    if (Emergency) begin
        next_state=EMERGENCY;
    end
    else begin
    case(current_state)
        Empty:if (Entry) begin
            next_state=Occupied;
        end
        Occupied: if (Entry) begin
            next_state= Full;
        end 
        else if(Exit)begin
            next_state=Empty;
        end
        Full: begin
        if (Exit)
        next_state = Occupied;
        end
        EMERGENCY: begin
        next_state = Empty;
        end
        default:next_state=current_state;
    endcase
    end
end

always @(*) begin
    Empty_Out=1'b0;
    Occupied_Out = 1'b0;
    Full_Out = 1'b0;
    Emergency_Out = 1'b0;
    case (current_state)
        Empty:Empty_Out=1'b1;
        Occupied:Occupied_Out=1'b1;
        Full:Full_Out=1'b1;
        EMERGENCY:Emergency_Out=1'b1; 
        default:begin Empty_Out=1'b0;
    Occupied_Out = 1'b0;
    Full_Out = 1'b0;
    Emergency_Out = 1'b0;
    end
    endcase
end
endmodule

Level-5-Finite-State-Machines/tb_q44.v
module tb_q44;
reg Clock;
reg Reset;
reg Entry;
reg Exit;
reg Emergency;
wire Empty_Out;
wire Occupied_Out;
wire Full_Out;
wire Emergency_Out;

wire [2:0] Status;
assign Status = {Full_Out, Occupied_Out, Empty_Out};

Q44 dut(.Clock(Clock),.Reset(Reset),.Entry(Entry),.Exit(Exit),.Emergency(Emergency),.Empty_Out(Empty_Out),.Occupied_Out(Occupied_Out),.Full_Out(Full_Out),.Emergency_Out(Emergency_Out));

always #5 Clock=~Clock;

initial begin
    $dumpfile("q44.vcd");
    $dumpvars(0,tb_q44);
    $monitor("Clock=%b,Reset=%b,Entry=%b,Exit=%b,Emergency=%b,Status=%b,Emergency_out=%b",Clock,Reset,Entry,Exit,Emergency,Status,Emergency_Out);
    Clock=0;Reset=1;Entry=0;Exit=0;Emergency=0;#10;
    Reset=0;Entry=1;Exit=0;Emergency=0;#10;
    Reset=0;Entry=1;Exit=0;Emergency=0;#10;
    Reset=0;Entry=0;Exit=1;Emergency=0;#10;
    Reset=0;Entry=0;Exit=1;Emergency=0;#10;
    Reset=0;Entry=0;Exit=0;Emergency=1;#10;
    Reset=0;Entry=0;Exit=0;Emergency=1;#10;
    Reset=0;Entry=1;Exit=0;Emergency=1;#10;
    $finish;
end
endmodule

Level-5-Finite-State-Machines/q44.vcd
$date
	Sun Aug 16 14:38:44 2026
$end
$version
	Icarus Verilog
$end
$timescale
	1s
$end
$scope module tb_q44 $end
$var wire 3 ! Status [2:0] $end
$var wire 1 " Occupied_Out $end
$var wire 1 # Full_Out $end
$var wire 1 $ Empty_Out $end
$var wire 1 % Emergency_Out $end
$var reg 1 & Clock $end
$var reg 1 ' Emergency $end
$var reg 1 ( Entry $end
$var reg 1 ) Exit $end
$var reg 1 * Reset $end
$scope module dut $end
$var wire 1 & Clock $end
$var wire 1 ' Emergency $end
$var wire 1 ( Entry $end
$var wire 1 ) Exit $end
$var wire 1 * Reset $end
$var wire 3 + Status [2:0] $end
$var parameter 2 , EMERGENCY $end
$var parameter 2 - Empty $end
$var parameter 2 . Full $end
$var parameter 2 / Occupied $end
$var reg 1 % Emergency_Out $end
$var reg 1 $ Empty_Out $end
$var reg 1 # Full_Out $end
$var reg 1 " Occupied_Out $end
$var reg 2 0 current_state [1:0] $end
$var reg 2 1 next_state [1:0] $end
$upscope $end
$upscope $end
$enddefinitions $end
$comment Show the parameter values. $end
$dumpall
b1 /
b10 .
b0 -
b11 ,
$end
#0
$dumpvars
b0 1
b0 0
b1 +
1*
0)
0(
0'
0&
0%
1$
0#
0"
b1 !
$end
#5
1&
#10
b1 1
0&
1(
0*
#15
1"
b10 +
b10 !
0$
b10 1
b1 0
1&
#20
0&
#25
1#
b100 +
b100 !
0"
b10 0
1&
#30
b1 1
0&
1)
0(
#35
1"
b10 +
b10 !
0#
b0 1
b1 0
1&
#40
0&
#45
1$
b1 +
b1 !
0"
b0 0
1&
#50
b11 1
0&
1'
0)
#55
1%
b0 +
b0 !
0$
b11 0
1&
#60
0&
#65
1&
#70
0&
1(
