Level-5-Finite-State-Machines/Q45_UARTtx.v
module Q45 (
    input wire Clock,
    input wire Reset,
    input wire Start,
    input wire [7:0] Data, 
    output reg Tx,Busy
);
    reg [1:0] current_state;
    reg [1:0] next_state;
    parameter IDLE=2'b00;
    parameter START=2'b01;
    parameter DATA=2'b10;
    parameter STOP=2'b11;
    reg [7:0] data_reg;
    reg [2:0] bit_count;

    always @(posedge Clock or posedge Reset) begin
    if (Reset) begin
        current_state <= IDLE;
        bit_count <= 3'b000;
    end
    else begin
        current_state <= next_state;

        if (current_state == IDLE && Start) begin
            data_reg <= Data;
            bit_count <= 3'b000;
        end

        else if (current_state == DATA && bit_count < 3'd7) begin
            bit_count <= bit_count + 1'b1;
        end
    end
end

    always @(*) begin
        next_state=current_state;
        case (current_state)
            IDLE:if (Start) begin
                next_state=START;
            end 
            START:begin 
                next_state=DATA;
            end
            DATA:if (bit_count==3'd7) begin
                next_state=STOP;
            end
            else begin
                next_state=DATA;
            end
            STOP:begin
                next_state=IDLE;
            end
            default:next_state=IDLE;
        endcase
    end

always @(*) begin
    Tx=1'b0;
    Busy=1'b0;
    case (current_state)
        IDLE:begin 
        Tx=1;
        Busy=1'b0;
        end
        START:begin 
        Tx=0;
        Busy=1;
        end
        DATA:begin 
            Tx=data_reg[bit_count];
            Busy=1;
        end
        STOP:begin 
            Tx=1;
            Busy=1;
        end 
        default:begin
            Tx=1'b0;
            Busy=1'b0;
        end
    endcase
end
endmodule

Level-5-Finite-State-Machines/tb_q45.v
module tb_Q45;

reg Clock;
reg Reset;
reg Start;
reg [7:0] Data;

wire Tx;
wire Busy;

Q45 dut (
    .Clock(Clock),
    .Reset(Reset),
    .Start(Start),
    .Data(Data),
    .Tx(Tx),
    .Busy(Busy)
);

always #5 Clock = ~Clock;

initial begin

    $dumpfile("q45.vcd");
    $dumpvars(0, tb_Q45);

    $monitor("Clock=%b Reset=%b Start=%b Data=%b Tx=%b Busy=%b",Clock, Reset, Start, Data, Tx, Busy);
    Clock = 0;Reset = 1;Start = 0;
    Data = 8'b00000000;#10;
    Reset = 0;Data = 8'b10110010;Start = 1;#10;
    
    Start = 0;
    #100;

    Data = 8'b11001100;Start = 1;#10;

    Start = 0;#100;
    $finish;

end

endmodule

Level-5-Finite-State-Machines/q45.vcd
$date
	Tue Aug 25 23:02:43 2026
$end
$version
	Icarus Verilog
$end
$timescale
	1s
$end
$scope module tb_Q45 $end
$var wire 1 ! Tx $end
$var wire 1 " Busy $end
$var reg 1 # Clock $end
$var reg 8 $ Data [7:0] $end
$var reg 1 % Reset $end
$var reg 1 & Start $end
$scope module dut $end
$var wire 1 # Clock $end
$var wire 8 ' Data [7:0] $end
$var wire 1 % Reset $end
$var wire 1 & Start $end
$var parameter 2 ( DATA $end
$var parameter 2 ) IDLE $end
$var parameter 2 * START $end
$var parameter 2 + STOP $end
$var reg 1 " Busy $end
$var reg 1 ! Tx $end
$var reg 3 , bit_count [2:0] $end
$var reg 2 - current_state [1:0] $end
$var reg 8 . data_reg [7:0] $end
$var reg 2 / next_state [1:0] $end
$upscope $end
$upscope $end
$enddefinitions $end
$comment Show the parameter values. $end
$dumpall
b11 +
b1 *
b0 )
b10 (
$end
#0
$dumpvars
b0 /
bx .
b0 -
b0 ,
b0 '
0&
1%
b0 $
0#
0"
1!
$end
#5
1#
#10
b1 /
0#
1&
b10110010 $
b10110010 '
0%
#15
1"
0!
b10 /
b10110010 .
b1 -
1#
#20
b10 /
0#
0&
#25
1"
b10 -
1#
#30
0#
#35
1!
1"
b1 ,
1#
#40
0#
#45
1"
0!
b10 ,
1#
#50
0#
#55
1"
b11 ,
1#
#60
0#
#65
1!
1"
b100 ,
1#
#70
0#
#75
1"
1!
b101 ,
1#
#80
0#
#85
1"
0!
b110 ,
1#
#90
0#
#95
1!
1"
b11 /
b111 ,
1#
#100
0#
#105
1"
1!
b0 /
b11 -
1#
#110
0#
#115
0"
1!
b0 -
1#
#120
b1 /
0#
1&
b11001100 $
b11001100 '
#125
1"
0!
b10 /
b0 ,
b11001100 .
b1 -
1#
#130
b10 /
0#
0&
#135
1"
b10 -
1#
#140
0#
#145
1"
b1 ,
1#
#150
0#
#155
1!
1"
b10 ,
1#
#160
0#
#165
1"
1!
b11 ,
1#
#170
0#
#175
1"
0!
b100 ,
1#
#180
0#
#185
1"
b101 ,
1#
#190
0#
#195
1!
1"
b110 ,
1#
#200
0#
#205
1"
1!
b11 /
b111 ,
1#
#210
0#
#215
1"
1!
b0 /
b11 -
1#
#220
0#
#225
0"
1!
b0 -
1#
