level_3/q4.v
module q4 (
    input wire [3:0] bcd, output reg [6:0] seg
);
    always @(*) begin
        case(bcd)
        4'b0000: seg= 7'b1111110;
        4'b0001: seg= 7'b0110000;
        4'b0010: seg= 7'b1101101;
        4'b0011: seg= 7'b1111001;
        4'b0100: seg= 7'b0110011;
        4'b0101: seg= 7'b1011011;
        4'b0110: seg= 7'b1011111;
        4'b0111: seg= 7'b1110000;
        4'b1000: seg= 7'b1111111;
        4'b1001: seg= 7'b1111011;
        default: seg= 7'b0000000;
        endcase
    end
endmodule

level_3/tb_q4.v
module tb_q4;
reg [3:0] bcd;
wire [6:0] seg;

q4 uut(.bcd(bcd),.seg(seg));

initial begin
    $dumpfile("q4.vcd");
    $dumpvars(0,tb_q4);
    $monitor("bcd=%b,seg=%b",bcd,seg);

    bcd=4'b0000;#10;
    bcd=4'b0001;#10;
    bcd=4'b0010;#10;
    bcd=4'b0011;#10;
    bcd=4'b0100;#10;
    bcd=4'b0101;#10;
    bcd=4'b0110;#10;
    bcd=4'b0111;#10;
    bcd=4'b1000;#10;
    bcd=4'b1001;#10;
    bcd=4'b1010;#10;
    $finish;
end

endmodule

level_3/q4.vcd
$date
	Tue Jul 07 23:23:04 2026
$end
$version
	Icarus Verilog
$end
$timescale
	1s
$end
$scope module tb_q4 $end
$var wire 7 ! seg [6:0] $end
$var reg 4 " bcd [3:0] $end
$scope module uut $end
$var wire 4 # bcd [3:0] $end
$var reg 7 $ seg [6:0] $end
$upscope $end
$upscope $end
$enddefinitions $end
$comment Show the parameter values. $end
$dumpall
$end
#0
$dumpvars
b1111110 $
b0 #
b0 "
b1111110 !
$end
#10
b110000 !
b110000 $
b1 "
b1 #
#20
b1101101 !
b1101101 $
b10 "
b10 #
#30
b1111001 !
b1111001 $
b11 "
b11 #
#40
b110011 !
b110011 $
b100 "
b100 #
#50
b1011011 !
b1011011 $
b101 "
b101 #
#60
b1011111 !
b1011111 $
b110 "
b110 #
#70
b1110000 !
b1110000 $
b111 "
b111 #
#80
b1111111 !
b1111111 $
b1000 "
b1000 #
#90
b1111011 !
b1111011 $
b1001 "
b1001 #
#100
b0 !
b0 $
b1010 "
b1010 #
