level_3/q5.v
module q5 (
    input wire [1:0] in1,input wire [1:0] in2, output reg greater,less,equal
);
    always @(*) begin
        if(in1>in2)
         begin
            greater=1'b1;
            less=1'b0;
            equal=1'b0;
         end
        else if (in1==in2) begin
            greater=1'b0;
            less=1'b0;
            equal=1'b1;
        end
        else
         begin
            greater=1'b0;
            less=1'b1;
            equal=1'b0;
         end
    end
endmodule

level_3/tb_q5.v
module tb_q5;
reg [1:0] in1;
reg [1:0] in2;
wire greater,less,equal;

q5 uut(.in1(in1),.in2(in2),.greater(greater),.less(less),.equal(equal));

initial begin
    $dumpfile("q5.vcd");
    $dumpvars(0,tb_q5);
    $monitor("a=%b,b=%b,greater=%b,equal=%b,less=%b",in1,in2,greater,equal,less);

    in1=2'b00; in2=2'b00; #10;
    in1=2'b01; in2=2'b01; #10;
    in1=2'b10; in2=2'b10; #10;
    in1=2'b11; in2=2'b11; #10;
    in1=2'b01; in2=2'b00; #10;
    in1=2'b10; in2=2'b01; #10;
    in1=2'b11; in2=2'b10; #10;
    in1=2'b00; in2=2'b01; #10;
    in1=2'b01; in2=2'b10; #10;
    in1=2'b10; in2=2'b11; #10;

    $finish;
end
endmodule

level_3/q5.vcd
$date
	Wed Jul 08 23:51:30 2026
$end
$version
	Icarus Verilog
$end
$timescale
	1s
$end
$scope module tb_q5 $end
$var wire 1 ! less $end
$var wire 1 " greater $end
$var wire 1 # equal $end
$var reg 2 $ in1 [1:0] $end
$var reg 2 % in2 [1:0] $end
$scope module uut $end
$var wire 2 & in1 [1:0] $end
$var wire 2 ' in2 [1:0] $end
$var reg 1 # equal $end
$var reg 1 " greater $end
$var reg 1 ! less $end
$upscope $end
$upscope $end
$enddefinitions $end
$comment Show the parameter values. $end
$dumpall
$end
#0
$dumpvars
b0 '
b0 &
b0 %
b0 $
1#
0"
0!
$end
#10
b1 %
b1 '
b1 $
b1 &
#20
b10 %
b10 '
b10 $
b10 &
#30
b11 %
b11 '
b11 $
b11 &
#40
0#
1"
b0 %
b0 '
b1 $
b1 &
#50
b1 %
b1 '
b10 $
b10 &
#60
b10 %
b10 '
b11 $
b11 &
#70
1!
0"
b1 %
b1 '
b0 $
b0 &
#80
b10 %
b10 '
b1 $
b1 &
#90
b11 %
b11 '
b10 $
b10 &
