level_3/q6.v
module q6 (
    input wire [3:0] in1,input wire [3:0] in2, input wire [1:0] operator_code,output reg [3:0] out
);
    always @(*) begin
        case(operator_code)
        2'b00: out=in1+in2;
        2'b01: out=in1-in2;
        2'b10: out=in1&in2;
        2'b11: out=in1|in2;
        default: out=4'b0000;
        endcase
    end
endmodule

level_3/tb_q6.v
module tb_q6;
reg [3:0] in1;
reg [3:0] in2;
reg [1:0] operator_code;
wire [3:0] out;

q6 uut(.in1(in1),.in2(in2),.operator_code(operator_code),.out(out));

initial begin
    $dumpfile("q6.vcd");
    $dumpvars(0,tb_q6);
    $monitor("a=%b,b=%b,operator code=%b,output=%b",in1,in2,operator_code,out);
    operator_code=2'b00;in1=4'b1000;in2=4'b0011;#10;
    operator_code=2'b01;in1=4'b1000;in2=4'b0011;#10;
    operator_code=2'b10;in1=4'b1000;in2=4'b0011;#10;
    operator_code=2'b11;in1=4'b1000;in2=4'b0011;#10;
    operator_code=2'b00;in1=4'b1010;in2=4'b0010;#10;
    operator_code=2'b01;in1=4'b1100;in2=4'b0111;#10;
    operator_code=2'b10;in1=4'b1010;in2=4'b0011;#10;
    operator_code=2'b11;in1=4'b1001;in2=4'b0111;#10;
    end
endmodule

level_3/q6.vcd
$date
	Thu Jul 09 21:58:18 2026
$end
$version
	Icarus Verilog
$end
$timescale
	1s
$end
$scope module tb_q6 $end
$var wire 4 ! out [3:0] $end
$var reg 4 " in1 [3:0] $end
$var reg 4 # in2 [3:0] $end
$var reg 2 $ operator_code [1:0] $end
$scope module uut $end
$var wire 4 % in1 [3:0] $end
$var wire 4 & in2 [3:0] $end
$var wire 2 ' operator_code [1:0] $end
$var reg 4 ( out [3:0] $end
$upscope $end
$upscope $end
$enddefinitions $end
$comment Show the parameter values. $end
$dumpall
$end
#0
$dumpvars
b1011 (
b0 '
b11 &
b1000 %
b0 $
b11 #
b1000 "
b1011 !
$end
#10
b101 !
b101 (
b1 $
b1 '
#20
b0 !
b0 (
b10 $
b10 '
#30
b1011 !
b1011 (
b11 $
b11 '
#40
b1100 !
b1100 (
b10 #
b10 &
b1010 "
b1010 %
b0 $
b0 '
#50
b101 !
b101 (
b111 #
b111 &
b1100 "
b1100 %
b1 $
b1 '
#60
b10 !
b10 (
b11 #
b11 &
b1010 "
b1010 %
b10 $
b10 '
#70
b1111 !
b1111 (
b111 #
b111 &
b1001 "
b1001 %
b11 $
b11 '
