level_3/q7.v
module q7 (
    input wire [7:0] in,input wire [2:0] shift,output reg [7:0] out  
);
    always @(*) begin
        case(shift)
        3'b000: out=in;
        3'b001: out= in<<1;
        3'b010: out= in<<2;
        3'b011: out= in<<3;
        3'b100: out= in<<4;
        3'b101: out= in<<5;
        3'b110: out= in<<6;
        3'b111: out= in<<7;
        default: out=8'b00000000;
        endcase
    end
endmodule

level_3/tb_q7.v
module tb_q7;
reg [7:0] in;
reg [2:0] shift;
wire [7:0] out;

q7 uut(.in(in),.shift(shift),.out(out));

initial begin
    $dumpfile("q7.vcd");
    $dumpvars(0,tb_q7);
    $monitor("input=%b,shift by=%b,output=%b",in,shift,out);
    in=8'b10100101;shift=3'b110;#10;
    in=8'b10001100;shift=3'b101;#10;
    in=8'b10111110;shift=3'b111;#10;
    in=8'b10101101;shift=3'b100;#10;
    in=8'b11100101;shift=3'b010;#10;
    in=8'b10101101;shift=3'b011;#10;
    in=8'b10110101;shift=3'b001;#10;
    in=8'b11100101;shift=3'b000;#10;
    $finish;
end
endmodule

level_3/q7.vcd
$date
	Fri Jul 10 22:25:27 2026
$end
$version
	Icarus Verilog
$end
$timescale
	1s
$end
$scope module tb_q7 $end
$var wire 8 ! out [7:0] $end
$var reg 8 " in [7:0] $end
$var reg 3 # shift [2:0] $end
$scope module uut $end
$var wire 8 $ in [7:0] $end
$var wire 3 % shift [2:0] $end
$var reg 8 & out [7:0] $end
$upscope $end
$upscope $end
$enddefinitions $end
$comment Show the parameter values. $end
$dumpall
$end
#0
$dumpvars
b1000000 &
b110 %
b10100101 $
b110 #
b10100101 "
b1000000 !
$end
#10
b10000000 !
b10000000 &
b101 #
b101 %
b10001100 "
b10001100 $
#20
b0 !
b0 &
b111 #
b111 %
b10111110 "
b10111110 $
#30
b11010000 !
b11010000 &
b100 #
b100 %
b10101101 "
b10101101 $
#40
b10010100 !
b10010100 &
b10 #
b10 %
b11100101 "
b11100101 $
#50
b1101000 !
b1101000 &
b11 #
b11 %
b10101101 "
b10101101 $
#60
b1101010 !
b1101010 &
b1 #
b1 %
b10110101 "
b10110101 $
#70
b11100101 !
b11100101 &
b0 #
b0 %
b11100101 "
b11100101 $
